odoo/addons/l10n_th_multicurrency_revaluation/README.rst
odoo/addons/l10n_th_multicurrency_revaluation/__init__.py
odoo/addons/l10n_th_multicurrency_revaluation/__manifest__.py
odoo/addons/l10n_th_multicurrency_revaluation/i18n/l10n_th_multicurrency_revaluation.pot
odoo/addons/l10n_th_multicurrency_revaluation/models/__init__.py
odoo/addons/l10n_th_multicurrency_revaluation/models/account_account.py
odoo/addons/l10n_th_multicurrency_revaluation/models/account_move.py
odoo/addons/l10n_th_multicurrency_revaluation/models/res_company.py
odoo/addons/l10n_th_multicurrency_revaluation/models/res_config.py
odoo/addons/l10n_th_multicurrency_revaluation/readme/CONFIGURE.rst
odoo/addons/l10n_th_multicurrency_revaluation/readme/CONTRIBUTORS.rst
odoo/addons/l10n_th_multicurrency_revaluation/readme/DESCRIPTION.rst
odoo/addons/l10n_th_multicurrency_revaluation/readme/USAGE.rst
odoo/addons/l10n_th_multicurrency_revaluation/report/__init__.py
odoo/addons/l10n_th_multicurrency_revaluation/report/currency_unrealized_report.py
odoo/addons/l10n_th_multicurrency_revaluation/report/currency_unrealized_report_xlsx.py
odoo/addons/l10n_th_multicurrency_revaluation/report/report.xml
odoo/addons/l10n_th_multicurrency_revaluation/report/unrealized_currency_gain_loss.xml
odoo/addons/l10n_th_multicurrency_revaluation/security/ir.model.access.csv
odoo/addons/l10n_th_multicurrency_revaluation/security/security.xml
odoo/addons/l10n_th_multicurrency_revaluation/static/description/icon.png
odoo/addons/l10n_th_multicurrency_revaluation/static/description/index.html
odoo/addons/l10n_th_multicurrency_revaluation/static/src/scss/reports.scss
odoo/addons/l10n_th_multicurrency_revaluation/tests/__init__.py
odoo/addons/l10n_th_multicurrency_revaluation/tests/test_multicurrency_revaluation.py
odoo/addons/l10n_th_multicurrency_revaluation/views/account_move_line_views.xml
odoo/addons/l10n_th_multicurrency_revaluation/views/account_move_views.xml
odoo_addon_l10n_th_multicurrency_revaluation-15.0.1.1.0.dist-info/METADATA
odoo_addon_l10n_th_multicurrency_revaluation-15.0.1.1.0.dist-info/WHEEL
odoo_addon_l10n_th_multicurrency_revaluation-15.0.1.1.0.dist-info/top_level.txt
odoo_addon_l10n_th_multicurrency_revaluation-15.0.1.1.0.dist-info/RECORD
